osc_transformers/__init__.py
osc_transformers/__main__.py
osc_transformers/block_manager.py
osc_transformers/registry.py
osc_transformers/scheduler.py
osc_transformers/sequence.py
osc_transformers/architectures/__init__.py
osc_transformers/architectures/autoregressive.py
osc_transformers/attention/__init__.py
osc_transformers/attention/base.py
osc_transformers/attention/paged_attention.py
osc_transformers/embedding/__init__.py
osc_transformers/embedding/base.py
osc_transformers/embedding/vocab.py
osc_transformers/feedforward/__init__.py
osc_transformers/feedforward/base.py
osc_transformers/feedforward/swiglu.py
osc_transformers/head/__init__.py
osc_transformers/head/base.py
osc_transformers/head/lm.py
osc_transformers/normalization/__init__.py
osc_transformers/normalization/base.py
osc_transformers/normalization/rmsnorm.py
osc_transformers/ops/__init__.py
osc_transformers/ops/attention.py
osc_transformers/ops/rms_norm.py
osc_transformers/ops/swiglu.py
osc_transformers/ops/utils.py
osc_transformers/sampler/__init__.py
osc_transformers/sampler/base.py
osc_transformers/sampler/simple.py
osc_transformers-0.3.1.dist-info/METADATA
osc_transformers-0.3.1.dist-info/WHEEL
osc_transformers-0.3.1.dist-info/entry_points.txt
osc_transformers-0.3.1.dist-info/licenses/LICENSE
osc_transformers-0.3.1.dist-info/RECORD
