Metadata-Version: 2.4
Name: osc-transformers
Version: 0.3.1
Summary: 以配置文件的方式构建transformer模型
Author-email: wangmengdi <790990241@qq.com>
License-File: LICENSE
Requires-Python: >=3.10
Requires-Dist: catalogue>=2.0.1
Requires-Dist: confection>=0.1.4
Requires-Dist: flash-attn==2.8.3
Requires-Dist: jsonargparse>=4.40.1
Requires-Dist: loguru>=0.7.3
Requires-Dist: torch==2.8.0
Requires-Dist: xxhash>=3.4.1
